[
  {
    "ID": "STR_ITEM_RICE_NAME",
    "Korean": "벼",
    "English": -1,
    "Chinese": -1,
    "Japanese": -1
  },
  {
    "ID": "STR_ITEM_BEAN_NAME",
    "Korean": "콩",
    "English": -1,
    "Chinese": -1,
    "Japanese": -1
  },
  {
    "ID": "STR_ITEM_PEPPER_NAME",
    "Korean": "고추",
    "English": -1,
    "Chinese": -1,
    "Japanese": -1
  },
  {
    "ID": "STR_ITEM_WHITERICE_NAME",
    "Korean": "백미",
    "English": -1,
    "Chinese": -1,
    "Japanese": -1
  },
  {
    "ID": "STR_ITEM_BEANPULP_NAME",
    "Korean": "콩비지",
    "English": -1,
    "Chinese": -1,
    "Japanese": -1
  },
  {
    "ID": "STR_ITEM_PEPPERPOWDER_NAME",
    "Korean": "고춧가루",
    "English": -1,
    "Chinese": -1,
    "Japanese": -1
  },
  {
    "ID": "STR_ITEM_RICESYRUP_NAME",
    "Korean": "조청",
    "English": -1,
    "Chinese": -1,
    "Japanese": -1
  },
  {
    "ID": "STR_ITEM_BEANPASTE_NAME",
    "Korean": "장",
    "English": "",
    "Chinese": "",
    "Japanese": ""
  },
  {
    "ID": "STR_ITEM_RICEMEAL_NAME",
    "Korean": "별밥",
    "English": "",
    "Chinese": "",
    "Japanese": ""
  },
  {
    "ID": "STR_ITEM_TOFU_NAME",
    "Korean": "별두부",
    "English": "",
    "Chinese": "",
    "Japanese": ""
  },
  {
    "ID": "STR_ITEM_RICECAKE_NAME",
    "Korean": "별떡",
    "English": "",
    "Chinese": "",
    "Japanese": ""
  },
  {
    "ID": "STR_ITEM_CANDY_NAME",
    "Korean": "별엿",
    "English": "",
    "Chinese": "",
    "Japanese": ""
  },
  {
    "ID": "STR_ITEM_TTEOKBOKKI_NAME",
    "Korean": "별떡볶이",
    "English": "",
    "Chinese": "",
    "Japanese": ""
  },
  {
    "ID": "STR_ITEM_TOFUSTEW_NAME",
    "Korean": "별두부찌개",
    "English": "",
    "Chinese": "",
    "Japanese": ""
  },
  {
    "ID": "STR_ITEM_RICE_DESC",
    "Korean": "벼",
    "English": -1,
    "Chinese": -1,
    "Japanese": -1
  },
  {
    "ID": "STR_ITEM_BEAN_DESC",
    "Korean": "콩",
    "English": -1,
    "Chinese": -1,
    "Japanese": -1
  },
  {
    "ID": "STR_ITEM_PEPPER_DESC",
    "Korean": "고추",
    "English": -1,
    "Chinese": -1,
    "Japanese": -1
  },
  {
    "ID": "STR_ITEM_WHITERICE_DESC",
    "Korean": "백미",
    "English": -1,
    "Chinese": -1,
    "Japanese": -1
  },
  {
    "ID": "STR_ITEM_BEANPULP_DESC",
    "Korean": "콩비지",
    "English": -1,
    "Chinese": -1,
    "Japanese": -1
  },
  {
    "ID": "STR_ITEM_PEPPERPOWDER_DESC",
    "Korean": "고춧가루",
    "English": -1,
    "Chinese": -1,
    "Japanese": -1
  },
  {
    "ID": "STR_ITEM_RICESYRUP_DESC",
    "Korean": "조청",
    "English": -1,
    "Chinese": -1,
    "Japanese": -1
  },
  {
    "ID": "STR_ITEM_BEANPASTE_DESC",
    "Korean": "장",
    "English": "",
    "Chinese": "",
    "Japanese": ""
  },
  {
    "ID": "STR_ITEM_RICEMEAL_DESC",
    "Korean": "별밥",
    "English": "",
    "Chinese": "",
    "Japanese": ""
  },
  {
    "ID": "STR_ITEM_TOFU_DESC",
    "Korean": "별두부",
    "English": "",
    "Chinese": "",
    "Japanese": ""
  },
  {
    "ID": "STR_ITEM_RICECAKE_DESC",
    "Korean": "별떡",
    "English": "",
    "Chinese": "",
    "Japanese": ""
  },
  {
    "ID": "STR_ITEM_CANDY_DESC",
    "Korean": "별엿",
    "English": "",
    "Chinese": "",
    "Japanese": ""
  },
  {
    "ID": "STR_ITEM_TTEOKBOKKI_DESC",
    "Korean": "별떡볶이",
    "English": "",
    "Chinese": "",
    "Japanese": ""
  },
  {
    "ID": "STR_ITEM_TOFUSTEW_DESC",
    "Korean": "별두부찌개",
    "English": "",
    "Chinese": "",
    "Japanese": ""
  },
  {
    "ID": "STR_BUILDING_HOUSE_NAME",
    "Korean": "집",
    "English": "",
    "Chinese": "",
    "Japanese": ""
  },
  {
    "ID": "STR_BUILDING_FARM_NAME",
    "Korean": "밭",
    "English": "",
    "Chinese": "",
    "Japanese": ""
  },
  {
    "ID": "STR_BUILDING_RICEFARM_NAME",
    "Korean": "쌀농장",
    "English": "",
    "Chinese": "",
    "Japanese": ""
  },
  {
    "ID": "STR_BUILDING_BEANFARM_NAME",
    "Korean": "콩농장",
    "English": "",
    "Chinese": "",
    "Japanese": ""
  },
  {
    "ID": "STR_BUILDING_PEPPERFARM_NAME",
    "Korean": "고추농장",
    "English": "",
    "Chinese": "",
    "Japanese": ""
  },
  {
    "ID": "STR_BUILDING_FERMENTROOM_NAME",
    "Korean": "발효공방",
    "English": "",
    "Chinese": "",
    "Japanese": ""
  },
  {
    "ID": "STR_BUILDING_POT_NAME",
    "Korean": "별가마솥",
    "English": "",
    "Chinese": "",
    "Japanese": ""
  },
  {
    "ID": "STR_BUILDING_MILL_NAME",
    "Korean": "별방앗간",
    "English": "",
    "Chinese": "",
    "Japanese": ""
  },
  {
    "ID": "STR_BUILDING_RESTAURANT_NAME",
    "Korean": "별식당",
    "English": "",
    "Chinese": "",
    "Japanese": ""
  },
  {
    "ID": "STR_BUILDING_HOUSE_DESC",
    "Korean": "집",
    "English": "",
    "Chinese": "",
    "Japanese": ""
  },
  {
    "ID": "STR_BUILDING_FARM_DESC",
    "Korean": "밭",
    "English": "",
    "Chinese": "",
    "Japanese": ""
  },
  {
    "ID": "STR_BUILDING_RICEFARM_DESC",
    "Korean": "쌀농장",
    "English": "",
    "Chinese": "",
    "Japanese": ""
  },
  {
    "ID": "STR_BUILDING_BEANFARM_DESC",
    "Korean": "콩농장",
    "English": "",
    "Chinese": "",
    "Japanese": ""
  },
  {
    "ID": "STR_BUILDING_PEPPERFARM_DESC",
    "Korean": "고추농장",
    "English": "",
    "Chinese": "",
    "Japanese": ""
  },
  {
    "ID": "STR_BUILDING_FERMENTROOM_DESC",
    "Korean": "발효공방",
    "English": "",
    "Chinese": "",
    "Japanese": ""
  },
  {
    "ID": "STR_BUILDING_POT_DESC",
    "Korean": "별가마솥",
    "English": "",
    "Chinese": "",
    "Japanese": ""
  },
  {
    "ID": "STR_BUILDING_MILL_DESC",
    "Korean": "별방앗간",
    "English": "",
    "Chinese": "",
    "Japanese": ""
  },
  {
    "ID": "STR_BUILDING_RESTAURANT_DESC",
    "Korean": "별식당",
    "English": "",
    "Chinese": "",
    "Japanese": ""
  },
  {
    "ID": "STR_OPTION_GAMESETTING",
    "Korean": "게임설정",
    "English": "Game",
    "Chinese": -1,
    "Japanese": -1
  },
  {
    "ID": "STR_OPTION_GAMESETTING_ON",
    "Korean": "켜짐",
    "English": "On",
    "Chinese": -1,
    "Japanese": -1
  },
  {
    "ID": "STR_OPTION_GAMESETTING_OFF",
    "Korean": "꺼짐",
    "English": "Off",
    "Chinese": -1,
    "Japanese": -1
  },
  {
    "ID": "STR_OPTION_GAMESETTING_SOUND",
    "Korean": "사운드",
    "English": "Sound",
    "Chinese": -1,
    "Japanese": -1
  },
  {
    "ID": "STR_OPTION_GAMESETTING_SOUND_BGM",
    "Korean": "배경음",
    "English": "BGM",
    "Chinese": -1,
    "Japanese": -1
  },
  {
    "ID": "STR_OPTION_GAMESETTING_SOUND_SFX",
    "Korean": "효과음",
    "English": "SFX",
    "Chinese": -1,
    "Japanese": -1
  },
  {
    "ID": "STR_OPTION_GAMESETTING_SCREEN",
    "Korean": "게임환경",
    "English": "Environments",
    "Chinese": -1,
    "Japanese": -1
  },
  {
    "ID": "STR_OPTION_GAMESETTING_SCREEN_FRAME",
    "Korean": "프레임 설정",
    "English": "FPS Settings",
    "Chinese": -1,
    "Japanese": -1
  },
  {
    "ID": "STR_OPTION_GAMESETTING_SCREEN_FRAME_30",
    "Korean": "30Fps",
    "English": "30Fps",
    "Chinese": -1,
    "Japanese": -1
  },
  {
    "ID": "STR_OPTION_GAMESETTING_SCREEN_FRAME_60",
    "Korean": "60Fps",
    "English": "60Fps",
    "Chinese": -1,
    "Japanese": -1
  },
  {
    "ID": "STR_OPTION_GAMESETTING_SCREEN_GRAPHICS",
    "Korean": "그래픽 설정",
    "English": "Graphics",
    "Chinese": -1,
    "Japanese": -1
  },
  {
    "ID": "STR_OPTION_GAMESETTING_SCREEN_GRAPHICS_LOW",
    "Korean": "낮음",
    "English": "Low",
    "Chinese": -1,
    "Japanese": -1
  },
  {
    "ID": "STR_OPTION_GAMESETTING_SCREEN_GRAPHICS_DEFAULT",
    "Korean": "일반",
    "English": "Default",
    "Chinese": -1,
    "Japanese": -1
  },
  {
    "ID": "STR_OPTION_GAMESETTING_ALERT",
    "Korean": "알림",
    "English": "Notifications",
    "Chinese": -1,
    "Japanese": -1
  },
  {
    "ID": "STR_OPTION_GAMESETTING_ALERT_PUSH",
    "Korean": "푸시 알림",
    "English": "Push Notifications",
    "Chinese": -1,
    "Japanese": -1
  },
  {
    "ID": "STR_OPTION_GAMESETTING_LANGUAGE_KOREAN",
    "Korean": "한국어",
    "English": "KOR",
    "Chinese": -1,
    "Japanese": -1
  },
  {
    "ID": "STR_OPTION_GAMESETTING_LANGUAGE_ENGLISH",
    "Korean": "ENG",
    "English": "ENG",
    "Chinese": -1,
    "Japanese": -1
  },
  {
    "ID": "STR_OPTION_GAMESETTING_LANGUAGE_POPUP",
    "Korean": "언어 변경",
    "English": "Change Language",
    "Chinese": -1,
    "Japanese": -1
  },
  {
    "ID": "STR_OPTION_GAMESETTING_LANGUAGE_POPUP_CONTENT",
    "Korean": "언어를 변경하기 위해\n게임을 재시작 할까요?",
    "English": "Restart the game to \napply the language change?",
    "Chinese": -1,
    "Japanese": -1
  },
  {
    "ID": "STR_OPTION_GAMESETTING_LANGUAGE_POPUP_YES",
    "Korean": "예",
    "English": "Yes",
    "Chinese": -1,
    "Japanese": -1
  },
  {
    "ID": "STR_OPTION_GAMESETTING_LANGUAGE_POPUP_NO",
    "Korean": "아니요",
    "English": "No",
    "Chinese": -1,
    "Japanese": -1
  },
  {
    "ID": "STR_OPTION_GAMESETTING_PIN",
    "Korean": "PIN ID : {0}",
    "English": "PIN ID : {0}",
    "Chinese": -1,
    "Japanese": -1
  },
  {
    "ID": "STR_OPTION_ACCOUNTSETTING",
    "Korean": "계정설정",
    "English": "Account",
    "Chinese": -1,
    "Japanese": -1
  },
  {
    "ID": "STR_OPTION_SERVICECENTER",
    "Korean": "고객센터",
    "English": "Service Center",
    "Chinese": -1,
    "Japanese": -1
  }
]